{"links": [{"source": 14118, "value": 1.571607061739414, "target": 14126}, {"source": "14122__0", "value": 0.18649736926993, "target": 14133}, {"source": "14122__1", "value": 1.3987303216312386, "target": 14126}, {"source": "14122__2", "value": 0.46624344054374633, "target": 14131}, {"source": "14122__3", "value": 1.5716070617394116, "target": 14123}, {"source": 14123, "value": 1.571607061739414, "target": 14118}, {"source": 14124, "value": 3.1024677364593645, "target": 14133}, {"source": "14125__0", "value": 0.017617379755530363, "target": 14133}, {"source": "14125__1", "value": 0.1321303530887169, "target": 14126}, {"source": 14126, "value": 3.1024677364593645, "target": 14124}, {"source": 14127, "value": 2.6934175145151755, "target": 14133}, {"source": 14129, "value": 2.2238468860131464, "target": 14131}, {"source": 14131, "value": 2.6934175145151755, "target": 14127}, {"source": 14132, "value": 6.000000000000002, "target": -1}, {"source": 14133, "value": 6.000000000000002, "target": 14132}], "nodes": [{"data": {"name": "Precursor", "exchanges": [], "type": "product", "cum": 0.038992388996135864, "code": "e90555438d56e51ac87d2c1021a5fb09", "categories": [], "location": "GLO", "ind": 0.0, "unit": "kg", "amount": 0.8426966071128845}, "radius": 2.6193451028990236, "group": 0, "id": 14118}, {"data": {"name": "Precursor Mix", "exchanges": [{"comment": "production exchange of Precursor", "uncertainty type": 1, "amount": 1, "input": ["OrderedDict_Database", "e90555438d56e51ac87d2c1021a5fb09"], "type": "production"}, {"comment": "technosphere exchange of Bauxite Residue", "uncertainty type": 1, "amount": 1, "input": ["OrderedDict_Database", "a9f02b22787e6d8dec991c37450f3d58"], "type": "technosphere"}, {"comment": "technosphere exchange of Quartz", "uncertainty type": 1, "amount": 1, "input": ["OrderedDict_Database", "09d8ffd78d9e181ca1a8c076bae3e479"], "type": "technosphere"}, {"comment": "technosphere exchange of Graphite", "uncertainty type": 1, "amount": 1, "input": ["OrderedDict_Database", "800228bc46c70a45b32a727cf11e7025"], "type": "technosphere"}, {"comment": "technosphere exchange of Energy, electricity", "uncertainty type": 1, "amount": 1, "input": ["OrderedDict_Database", "440891b98348acaa325bb80b1e0080fb"], "type": "technosphere"}], "type": "process", "cum": 0.038992388996135864, "code": "831769795a6d8e6a8e1e66887cd4602d", "categories": [], "location": "GLO", "ind": 0.0, "unit": "kg", "amount": 0.8426966071128845}, "radius": 2.6193451028990236, "group": 1, "id": 14123}, {"data": {"name": "Fired Precursor", "exchanges": [], "type": "product", "cum": 0.07697383892771217, "code": "0f1a0240e2ffd88d0a648201aff9d5c6", "categories": [], "location": "GLO", "ind": 0.0, "unit": "kg", "amount": 0.75}, "radius": 5.170779560765607, "group": 2, "id": 14124}, {"data": {"name": "Energy, heat", "exchanges": [], "ext_link": ["Ecoinvent3_3_cutoff", "126f25761ab05443a96809d1fa471b05"], "type": "product", "cum": 0.0037153191739224185, "code": "2afad861f5b43c7c6f9cf0175d07dc59", "categories": [], "location": "GLO", "ind": 0.0, "unit": "kWh", "amount": 0.08500000089406967}, "radius": 0.24957955474041205, "group": 4, "id": "14125__0"}, {"data": {"name": "Energy, heat", "exchanges": [], "ext_link": ["Ecoinvent3_3_cutoff", "126f25761ab05443a96809d1fa471b05"], "type": "product", "cum": 0.0037153191739224185, "code": "2afad861f5b43c7c6f9cf0175d07dc59", "categories": [], "location": "GLO", "ind": 0.0, "unit": "kWh", "amount": 0.08500000089406967}, "radius": 0.24957955474041205, "group": 4, "id": "14125__1"}, {"data": {"name": "Precursor Firing", "exchanges": [{"comment": "production exchange of Fired Precursor", "uncertainty type": 1, "amount": 1, "input": ["OrderedDict_Database", "0f1a0240e2ffd88d0a648201aff9d5c6"], "type": "production"}, {"comment": "technosphere exchange of Precursor", "uncertainty type": 1, "amount": 1, "input": ["OrderedDict_Database", "e90555438d56e51ac87d2c1021a5fb09"], "type": "technosphere"}, {"comment": "technosphere exchange of Energy, electricity", "uncertainty type": 1, "amount": 1, "input": ["OrderedDict_Database", "440891b98348acaa325bb80b1e0080fb"], "type": "technosphere"}, {"comment": "technosphere exchange of Energy, heat", "uncertainty type": 1, "amount": 1, "input": ["OrderedDict_Database", "2afad861f5b43c7c6f9cf0175d07dc59"], "type": "technosphere"}], "type": "process", "cum": 0.07697383892771217, "code": "52c9bdcc760af781082e46350cf35aeb", "categories": [], "location": "GLO", "ind": 0.0, "unit": "kg", "amount": 0.75}, "radius": 5.170779560765607, "group": 5, "id": 14126}, {"data": {"name": "Activating Solution", "exchanges": [], "type": "product", "cum": 0.06682509006974341, "code": "0ec14153ed828c7aa40e26b9e71691ef", "categories": [], "location": "GLO", "ind": 0.0, "unit": "kg", "amount": 0.25}, "radius": 4.489029190858626, "group": 6, "id": 14127}, {"data": {"name": "Sodium Silicate", "exchanges": [], "ext_link": ["Ecoinvent3_3_cutoff", "80c983dedabc7b6e7424726269a2d177"], "type": "product", "cum": 0.05517479843294812, "code": "0b97986bafcaa3e80925da64bbd22e3b", "categories": [], "location": "GLO", "ind": 0.0, "unit": "kg", "amount": 0.0625}, "radius": 3.7064114766885776, "group": 7, "id": 14129}, {"data": {"name": "Activating Solution Mix", "exchanges": [{"comment": "production exchange of Activating Solution", "uncertainty type": 1, "amount": 1, "input": ["OrderedDict_Database", "0ec14153ed828c7aa40e26b9e71691ef"], "type": "production"}, {"comment": "technosphere exchange of Potassium Silicate", "uncertainty type": 1, "amount": 1, "input": ["OrderedDict_Database", "e002fa3e0b27f65cd89beb733132b2f3"], "type": "technosphere"}, {"comment": "technosphere exchange of Sodium Silicate", "uncertainty type": 1, "amount": 1, "input": ["OrderedDict_Database", "0b97986bafcaa3e80925da64bbd22e3b"], "type": "technosphere"}, {"comment": "technosphere exchange of Water", "uncertainty type": 1, "amount": 1, "input": ["OrderedDict_Database", "9caf077d1027a73da03c9919786e24c4"], "type": "technosphere"}, {"comment": "technosphere exchange of Energy, electricity", "uncertainty type": 1, "amount": 1, "input": ["OrderedDict_Database", "440891b98348acaa325bb80b1e0080fb"], "type": "technosphere"}], "type": "process", "cum": 0.06682509006974341, "code": "94f219ef36ee844c5758178c8b5298e4", "categories": [], "location": "GLO", "ind": 0.0, "unit": "kg", "amount": 0.25}, "radius": 4.489029190858626, "group": 8, "id": 14131}, {"data": {"name": "Cured IP", "exchanges": [], "type": "product", "cum": 0.1488631221330099, "code": "ae9e73ed0a3585a9acb626f10ca920bf", "categories": [], "location": "GLO", "ind": 0.0, "unit": "kg", "amount": 1.0}, "radius": 10.000000000000002, "group": 9, "id": 14132}, {"data": {"name": "Curing", "exchanges": [{"comment": "production exchange of Cured IP", "uncertainty type": 1, "amount": 1, "input": ["OrderedDict_Database", "ae9e73ed0a3585a9acb626f10ca920bf"], "type": "production"}, {"comment": "technosphere exchange of Fired Precursor", "uncertainty type": 1, "amount": 1, "input": ["OrderedDict_Database", "0f1a0240e2ffd88d0a648201aff9d5c6"], "type": "technosphere"}, {"comment": "technosphere exchange of Activating Solution", "uncertainty type": 1, "amount": 1, "input": ["OrderedDict_Database", "0ec14153ed828c7aa40e26b9e71691ef"], "type": "technosphere"}, {"comment": "technosphere exchange of Energy, electricity", "uncertainty type": 1, "amount": 1, "input": ["OrderedDict_Database", "440891b98348acaa325bb80b1e0080fb"], "type": "technosphere"}, {"comment": "technosphere exchange of Energy, heat", "uncertainty type": 1, "amount": 1, "input": ["OrderedDict_Database", "2afad861f5b43c7c6f9cf0175d07dc59"], "type": "technosphere"}], "type": "process", "cum": 0.1488631221330099, "code": "92fef462e5a37272071da17519eef1b4", "categories": [], "location": "GLO", "ind": 0.0, "unit": "kg", "amount": 1.0}, "radius": 10.000000000000002, "group": 10, "id": 14133}, {"data": {"name": "Energy, electricity", "exchanges": [], "ext_link": ["Ecoinvent3_3_cutoff", "cb3d8e82f9137eb0f0996850e549d699"], "type": "product", "cum": 0.08989045526157387, "code": "440891b98348acaa325bb80b1e0080fb", "categories": [], "location": "GLO", "ind": 0.0, "unit": "kWh", "amount": 0.19426966323360295}, "radius": 6.038463655307212, "group": 14, "id": "14122__0"}, {"data": {"name": "Energy, electricity", "exchanges": [], "ext_link": ["Ecoinvent3_3_cutoff", "cb3d8e82f9137eb0f0996850e549d699"], "type": "product", "cum": 0.08989045526157387, "code": "440891b98348acaa325bb80b1e0080fb", "categories": [], "location": "GLO", "ind": 0.0, "unit": "kWh", "amount": 0.19426966323360295}, "radius": 6.038463655307212, "group": 14, "id": "14122__1"}, {"data": {"name": "Energy, electricity", "exchanges": [], "ext_link": ["Ecoinvent3_3_cutoff", "cb3d8e82f9137eb0f0996850e549d699"], "type": "product", "cum": 0.08989045526157387, "code": "440891b98348acaa325bb80b1e0080fb", "categories": [], "location": "GLO", "ind": 0.0, "unit": "kWh", "amount": 0.19426966323360295}, "radius": 6.038463655307212, "group": 14, "id": "14122__2"}, {"data": {"name": "Energy, electricity", "exchanges": [], "ext_link": ["Ecoinvent3_3_cutoff", "cb3d8e82f9137eb0f0996850e549d699"], "type": "product", "cum": 0.08989045526157387, "code": "440891b98348acaa325bb80b1e0080fb", "categories": [], "location": "GLO", "ind": 0.0, "unit": "kWh", "amount": 0.19426966323360295}, "radius": 6.038463655307212, "group": 14, "id": "14122__3"}, {"data": {"cum": 0.14886312213300987, "name": "Final demand", "amount": 1, "ind": 1.4886312213300987e-07}, "radius": 10.0, "group": 15, "id": -1}]}